[
    {
        "key" : 1,
        "id" : "역순환 셔틀",
        "station_info" : "제2공학관",
        "coord" : [37.44879,126.95194],
        "next" : "제1공학관"
    },
    {
    "key" : 2,
    "id" : "역순환 셔틀",
    "station_info" : "제1공학관",
    "coord" : [37.44976,126.95187],
    "next" : "에너지자원신기술연구소"
    },
    {
    "key" : 3,
    "id" : "역순환 셔틀",
    "station_info" : "에너지자원신기술연구소",
    "coord" : [37.45347,126.95210],
    "next" : "38동"
    },
    {
    "key" : 4,
    "id" : "역순환 셔틀",
    "station_info" : "38동",
    "coord" : [37.45536,126.94975],
    "next" : "농생대"
    },
    {
    "key" : 5,
    "id" : "역순환 셔틀",
    "station_info" : "농생대",
    "coord" : [37.45700,126.94933],
    "next" : "자연대"
    },
    {
    "key" : 6,
    "id" : "역순환 셔틀",
    "station_info" : "자연대",
    "coord" : [37.46010,126.94893],
    "next" : "문화관"
    },
    {
    "key" : 7,
    "id" : "역순환 셔틀",
    "station_info" : "문화관",
    "coord" : [37.46148,126.94936],
    "next" : "법과대"
    },
    {
    "key" : 8,
    "id" : "역순환 셔틀",
    "station_info" : "법과대",
    "coord" : [37.46315,126.94897],
    "next" : "정문"
    },
    {
    "key" : 9,
    "id" : "역순환 셔틀",
    "station_info" : "정문",
    "coord" : [37.46519,126.94856],
    "next" : "경영대"
    },
    {
    "key" : 10,
    "id" : "역순환 셔틀",
    "station_info" : "경영대",
    "coord" : [37.46595,126.95108],
    "next" : "수의대"
    },
    {
    "key" : 11,
    "id" : "역순환 셔틀",
    "station_info" : "수의대",
    "coord" : [37.46600,126.95459],
    "next" : "기숙사"
    },
    {
    "key" : 12,
    "id" : "역순환 셔틀",
    "station_info" : "기숙사",
    "coord" : [37.46236,126.95728],
    "next" : "BK국제관"
    },
    {
    "key" : 13,
    "id" : "역순환 셔틀",
    "station_info" : "BK국제관",
    "coord" : [37.46544,126.95782],
    "next" : "호암교수회관"
    },
    {
    "key" : 14,
    "id" : "역순환 셔틀",
    "station_info" : "호암교수회관",
    "coord" : [37.46847,126.95823],
    "next" : "BK국제관"
    },
    {
    "key" : 15,
    "id" : "역순환 셔틀",
    "station_info" : "BK국제관",
    "coord" : [37.46544,126.95782],
    "next" : "기숙사"
    },
    {
    "key" : 16,
    "id" : "역순환 셔틀",
    "station_info" : "기숙사",
    "coord" : [37.46236,126.95728],
    "next" : "교수회관입구"
    },
    {
    "key" : 17,
    "id" : "역순환 셔틀",
    "station_info" : "교수회관입구",
    "coord" : [37.45592,126.95521],
    "next" : "유전공학연구소"
    },
    {
    "key" : 18,
    "id" : "역순환 셔틀",
    "station_info" : "유전공학연구소",
    "coord" : [37.45400,126.95379],
    "next" : "에너지자원신기술연구소"
    },
    {
    "key" : 19,
    "id" : "역순환 셔틀",
    "station_info" : "에너지자원신기술연구소",
    "coord" : [37.45347,126.95210],
    "next" : "신소재공동연구소"
    },
    {
    "key" : 20,
    "id" : "역순환 셔틀",
    "station_info" : "신소재공동연구소",
    "coord" : [37.45388,126.95072],
    "next" : "제2공학관"
    }
]
